{
  "name": "Jeanette Reese",
  "age": 26,
  "address": {
    "street": "Hutun Point",
    "city": "Fikwate",
    "state": "WY",
    "zip": "45046"
  },
  "contact": {
    "phone": "(565) 937-4846",
    "servicePhone": "800697985"
  },
  "birthday": "2004-07-03T07:12:08.556Z",
  "ip": "1.75.57.61",
  "foo": "bar",
  "profile": {
    "about": "Vujilave barpetwa obe mor jihoziv majmet biken iza pa fo hokpa caglelum ban upahiili dejog gadedi. Ilrugih bev jew jifavuv zudfomkih dasno kawuna wem ho wak olahogrej fok ta jad duhok odetri ani. Wopbogfa vezah muded ugu izkute zaf fi apdehfaj loduwa newa zerotlu eh dar kew. Age aj ewheruk muwzim ebajidhak levvabuk leojno dekzuf hurehru nirzeko zorok zupaw dakjedze luvab jo meca. Ref titatvu latgevuj wek wuhegakod obgo jit lodvabsiw sob budwahjul guvrubkuh bi ho uloustah patehuse gak mitsikku non.",
    "bio": "Cumvo nod ika tesizta bejarmo weeto gaopedo wu dokepzu deole aso dibanukon keup zizigac. Munonduv dednit ecuwam eb male weig ceghi sirip ka rapmubaz hahedi sunej supgicaro. Hehok ab riafo memla ud gu sofo pubsof mep zev ad et gozo muref ve. Vato tibutpit jas cimoli ca falukofo bam joror porot ehihizho tagguz pide rir lasud vedogzum ziobeufu jumgoce fospilha."
  },
  "apiKey": "8aedbe883d7ab2a9d4a0691eb331401c301213ae3901f7a2502b239cf802b4c3",
  "currency": {
    "code": "PGK",
    "name": "Papua New Guinea Kina"
  }
}