{
  "name": "Zachary Greer",
  "age": 50,
  "address": {
    "street": "Keze Parkway",
    "city": "Ublecag",
    "state": "AL",
    "zip": "43187"
  },
  "contact": {
    "phone": "(475) 383-4669",
    "servicePhone": "800596954"
  },
  "birthday": "1988-10-01T01:23:33.842Z",
  "ip": "192.9.164.91",
  "foo": "bar",
  "profile": {
    "about": "Suwezo ejo li hanejig zajracsa enfi kukmige mav kuga ru wi ked rop ewop pag toume ej la. Epjov agwin wa upeorsap sunuge ham diot liwu wannibpaj lummu an sittapze jogukmev. Solsegecu gu fonis bukatkeg sedpif uj ziuko vonmuj beh cefo so ala. Zupwuvo songa ida to uj no lasapba ne roji caldub ib retugu zawekki gajutuf. Bomjime feevoz nu az dev begas dabari se valkil awovorpin mageji cu gan.",
    "bio": "Juoze co zefcufoh jaorma ruglasu emo kadoz emo mocdebi wevokuk lufe dujmuzo bimnuce. Piruvuc dihucu era zecun mu bookdim bok duvnuz lu et udeti hobgowlij vag. Sewpi guz je ajri buk erazerjut cu ih athi je be liowifoh ifri mowrof wasica likmo pod ahe. Ot ocubeava migu suilu nefit vogoz moik heeju ka miade ezvo aho jazdikpub loih joz gesiw wu."
  },
  "apiKey": "2e21fa8a9b3ad8d3c7308717a4c2231242ea3357916edd980f4cde2d573276d9",
  "currency": {
    "code": "LRD",
    "name": "Liberia Dollar"
  }
}