{
  "name": "Leon Arnold",
  "age": 57,
  "address": {
    "street": "Ezbi Mill",
    "city": "Kijpitovo",
    "state": "ID",
    "zip": "17066"
  },
  "contact": {
    "phone": "(536) 314-3471",
    "servicePhone": "800684983"
  },
  "birthday": "2006-09-19T06:29:16.280Z",
  "ip": "174.121.246.198",
  "foo": "bar",
  "profile": {
    "about": "Hikkot fupoud ivokadud it noozwep wa biconit rebzehfag puj devmois nip now sodve ha. Azairve tid purogepom lakeva jicu nul wik ka giksuk feiko pulfahis penna he surkis haoji. Ma atahal boj miwa miudi ip tipicu evezuid judlovwi vizuzi bisru fa vutdateto. Wojga zonamjer upojid mecip wim dehfi na pev puple rejofij rocibwu biwasjud von mejup mosug hufsuhap vi koabo. Vemetude kobkojli roku ag vuulu bepa puwmicaz ga sobiswo ulfula tioci ebpa naekuuti. Deg fofok samuw cigu luvaku lovgi casra guifwod vitmib velko jat forukis fustebamu du tegjek niphet.",
    "bio": "Wead ginuop cebbeoj oduc biduw lagam hoeso ova avaziz jirri amzizjem goat fomic ifi sonbebir pih te. Iwa viwuce vim juk wiozeet rurrod rubmi kacehne gidvahe jakhuono sahho pizvuzi. Fopaj toja up owtaj zellu cemevso mukkiado niptadov nuz enle rafuj guzu sehjim ligofi ufitag dezag. En kimel ja lori nuphe nidlifit wes louv vubcamu lu refgedo lehu baj. Wam vofi vaen sanu putasu ritecdi pesis guriw fuc ez cek guhucgat hovculnuz fi omoipe. Hu dofap rubon ji vi of buhvusos fufuj aba pibup jocov domhigva gucato roci wun pa."
  },
  "apiKey": "5770d7edc742b6146704967a33b60cd959239305d952186bfc1c0c2995271fa8",
  "currency": {
    "code": "UAH",
    "name": "Ukraine Hryvnia"
  }
}